peewee_plus.py
peewee_plus-1.3.0.dist-info/LICENSE.md
peewee_plus-1.3.0.dist-info/METADATA
peewee_plus-1.3.0.dist-info/WHEEL
peewee_plus-1.3.0.dist-info/RECORD
