Metadata-Version: 2.1
Name: peewee-plus
Version: 1.3.0
Summary: Various extensions, helpers, and utilities for Peewee
Home-page: https://github.com/enpaul/peewee-plus/
License: MIT
Keywords: peewee,orm,extension,plguin,extra
Author: Ethan Paul
Author-email: 24588726+enpaul@users.noreply.github.com
Requires-Python: >=3.7.1,<4.0.0
Classifier: Development Status :: 5 - Production/Stable
Classifier: Environment :: Plugins
Classifier: Intended Audience :: Developers
Classifier: License :: OSI Approved :: MIT License
Classifier: Programming Language :: Python :: 3
Classifier: Programming Language :: Python :: 3.8
Classifier: Programming Language :: Python :: 3.9
Classifier: Programming Language :: Python :: 3.10
Classifier: Programming Language :: Python :: 3.11
Classifier: Programming Language :: Python :: 3
Classifier: Programming Language :: Python :: 3.10
Classifier: Programming Language :: Python :: 3.11
Classifier: Programming Language :: Python :: 3.7
Classifier: Programming Language :: Python :: 3.8
Classifier: Programming Language :: Python :: 3.9
Classifier: Programming Language :: Python :: Implementation :: CPython
Classifier: Topic :: Database
Classifier: Typing :: Typed
Requires-Dist: peewee (>=3.14.8,<4.0.0)
Project-URL: Repository, https://github.com/enpaul/peewee-plus/
